[
  {"date":"2026-01-08","sleep_total_min":450,"sleep_efficiency":0.88,"hr_resting":57,"steps":8200,"exercise_min":34,"active_energy_kcal":520},
  {"date":"2026-01-09","sleep_total_min":426,"sleep_efficiency":0.85,"hr_resting":58,"steps":7600,"exercise_min":28,"active_energy_kcal":480},
  {"date":"2026-01-10","sleep_total_min":378,"sleep_efficiency":0.78,"hr_resting":62,"steps":5900,"exercise_min":18,"active_energy_kcal":360},
  {"date":"2026-01-11","sleep_total_min":360,"sleep_efficiency":0.77,"hr_resting":63,"steps":5200,"exercise_min":14,"active_energy_kcal":320},
  {"date":"2026-01-12","sleep_total_min":420,"sleep_efficiency":0.86,"hr_resting":58,"steps":9300,"exercise_min":43,"active_energy_kcal":610},
  {"date":"2026-01-13","sleep_total_min":456,"sleep_efficiency":0.89,"hr_resting":56,"steps":10100,"exercise_min":52,"active_energy_kcal":690},
  {"date":"2026-01-14","sleep_total_min":432,"sleep_efficiency":0.86,"hr_resting":57,"steps":8800,"exercise_min":36,"active_energy_kcal":560},
  {"date":"2026-01-15","sleep_total_min":408,"sleep_efficiency":0.83,"hr_resting":59,"steps":7200,"exercise_min":24,"active_energy_kcal":430},
  {"date":"2026-01-16","sleep_total_min":384,"sleep_efficiency":0.81,"hr_resting":60,"steps":6500,"exercise_min":20,"active_energy_kcal":400},
  {"date":"2026-01-17","sleep_total_min":360,"sleep_efficiency":0.78,"hr_resting":63,"steps":5400,"exercise_min":14,"active_energy_kcal":330},
  {"date":"2026-01-18","sleep_total_min":372,"sleep_efficiency":0.80,"hr_resting":62,"steps":6000,"exercise_min":16,"active_energy_kcal":350},

  {"date":"2026-01-19","sleep_total_min":444,"sleep_efficiency":0.88,"hr_resting":57,"steps":9800,"exercise_min":49,"active_energy_kcal":650},
  {"date":"2026-01-20","sleep_total_min":462,"sleep_efficiency":0.90,"hr_resting":56,"steps":11050,"exercise_min":58,"active_energy_kcal":720},
  {"date":"2026-01-21","sleep_total_min":420,"sleep_efficiency":0.86,"hr_resting":58,"steps":8600,"exercise_min":35,"active_energy_kcal":550},
  {"date":"2026-01-22","sleep_total_min":396,"sleep_efficiency":0.82,"hr_resting":60,"steps":7000,"exercise_min":22,"active_energy_kcal":420},
  {"date":"2026-01-23","sleep_total_min":378,"sleep_efficiency":0.80,"hr_resting":61,"steps":6400,"exercise_min":19,"active_energy_kcal":390},
  {"date":"2026-01-24","sleep_total_min":354,"sleep_efficiency":0.77,"hr_resting":64,"steps":5200,"exercise_min":13,"active_energy_kcal":310},
  {"date":"2026-01-25","sleep_total_min":366,"sleep_efficiency":0.79,"hr_resting":63,"steps":6100,"exercise_min":17,"active_energy_kcal":360},
  {"date":"2026-01-26","sleep_total_min":438,"sleep_efficiency":0.88,"hr_resting":57,"steps":9600,"exercise_min":47,"active_energy_kcal":640},
  {"date":"2026-01-27","sleep_total_min":468,"sleep_efficiency":0.91,"hr_resting":55,"steps":11500,"exercise_min":61,"active_energy_kcal":760},
  {"date":"2026-01-28","sleep_total_min":426,"sleep_efficiency":0.86,"hr_resting":58,"steps":8700,"exercise_min":36,"active_energy_kcal":560},
  {"date":"2026-01-29","sleep_total_min":402,"sleep_efficiency":0.83,"hr_resting":60,"steps":7200,"exercise_min":23,"active_energy_kcal":430},
  {"date":"2026-01-30","sleep_total_min":378,"sleep_efficiency":0.81,"hr_resting":61,"steps":6500,"exercise_min":20,"active_energy_kcal":400},
  {"date":"2026-01-31","sleep_total_min":348,"sleep_efficiency":0.76,"hr_resting":65,"steps":5100,"exercise_min":12,"active_energy_kcal":300},

  {"date":"2026-02-01","sleep_total_min":360,"sleep_efficiency":0.78,"hr_resting":63,"steps":6000,"exercise_min":16,"active_energy_kcal":350},
  {"date":"2026-02-02","sleep_total_min":444,"sleep_efficiency":0.88,"hr_resting":57,"steps":9900,"exercise_min":50,"active_energy_kcal":670},
  {"date":"2026-02-03","sleep_total_min":474,"sleep_efficiency":0.92,"hr_resting":55,"steps":12100,"exercise_min":64,"active_energy_kcal":790},
  {"date":"2026-02-04","sleep_total_min":432,"sleep_efficiency":0.87,"hr_resting":58,"steps":9000,"exercise_min":38,"active_energy_kcal":580},
  {"date":"2026-02-05","sleep_total_min":402,"sleep_efficiency":0.83,"hr_resting":60,"steps":7100,"exercise_min":22,"active_energy_kcal":420},
  {"date":"2026-02-06","sleep_total_min":384,"sleep_efficiency":0.81,"hr_resting":61,"steps":6400,"exercise_min":20,"active_energy_kcal":400}
]
